notiondict/__init__.py
notiondict/config.yml
notiondict/get_active_window_title_macos.scpt
notiondict/notiondict.py
notiondict-0.1.1.dist-info/LICENSE
notiondict-0.1.1.dist-info/METADATA
notiondict-0.1.1.dist-info/WHEEL
notiondict-0.1.1.dist-info/entry_points.txt
notiondict-0.1.1.dist-info/top_level.txt
notiondict-0.1.1.dist-info/RECORD
