Metadata-Version: 2.1
Name: notiondict
Version: 0.1.1
Summary: A high customized dictionary
Home-page: https://github.com/pixelhegel/notiondict
Author: Pixelhegel
Author-email: Pixelhegel@gmail.com
License: Apache License
Keywords: dictionary notification tool
Classifier: Development Status :: 4 - Beta
Classifier: Intended Audience :: Developers
Classifier: License :: OSI Approved :: Apache Software License
Classifier: Natural Language :: English
Classifier: Programming Language :: Python :: 3
Classifier: Programming Language :: Python :: 3.6
Classifier: Programming Language :: Python :: 3.7
Classifier: Programming Language :: Python :: 3.8
Classifier: Programming Language :: Python :: 3.9
License-File: LICENSE
Requires-Dist: readmdict
Requires-Dist: requests
Requires-Dist: docopt
Requires-Dist: pyclip
Requires-Dist: PyYAML
